jumandic
