Metadata-Version: 2.1
Name: jumandic
Version: 1.0.0
Summary: JumanDic packaged for use from Python
Home-page: https://github.com/polm/jumandic-py
Author: Paul O'Leary McCann
Author-email: polm@dampfkraft.com
License: UNKNOWN
Platform: UNKNOWN
Classifier: Programming Language :: Python :: 3
Classifier: License :: OSI Approved :: MIT License
Classifier: Operating System :: OS Independent
Classifier: Natural Language :: Japanese
